vulcan/__init__.py
vulcan/core/__init__.py
vulcan/core/application.py
vulcan/core/config.py
vulcan/core/auth/__init__.py
vulcan/core/auth/schemas/__init__.py
vulcan/core/auth/schemas/jwt.py
vulcan/core/auth/services/__init__.py
vulcan/core/auth/services/jwt.py
vulcan/core/db/db_core.py
vulcan/core/enum/__init__.py
vulcan/core/enum/status.py
vulcan/core/enum/synchronizesession.py
vulcan/core/exceptions/__init__.py
vulcan/core/exceptions/base.py
vulcan/core/exceptions/token.py
vulcan/core/exceptions/user.py
vulcan/core/fastapi/__init__.py
vulcan/core/fastapi/dependencies/__init__.py
vulcan/core/fastapi/dependencies/logging.py
vulcan/core/fastapi/dependencies/permission.py
vulcan/core/fastapi/middlewares/__init__.py
vulcan/core/fastapi/middlewares/authentication.py
vulcan/core/fastapi/middlewares/response_log.py
vulcan/core/fastapi/schemas/__init__.py
vulcan/core/fastapi/schemas/current_user.py
vulcan/core/helpers/__init__.py
vulcan/core/helpers/redis.py
vulcan/core/helpers/cache/__init__.py
vulcan/core/helpers/cache/cache_manager.py
vulcan/core/helpers/cache/cache_tag.py
vulcan/core/helpers/cache/custom_key_maker.py
vulcan/core/helpers/cache/redis_backend.py
vulcan/core/helpers/cache/base/__init__.py
vulcan/core/helpers/cache/base/backend.py
vulcan/core/helpers/cache/base/key_maker.py
vulcan/core/mixins/__init__.py
vulcan/core/mixins/timestamp_mixin.py
vulcan/core/user/__init__.py
vulcan/core/user/schemas/__init__.py
vulcan/core/user/schemas/user.py
vulcan/core/user/services/__init__.py
vulcan/core/user/services/user.py
vulcan/core/utils/__init__.py
vulcan/core/utils/http_util.py
vulcan/core/utils/json_util.py
vulcan/core/utils/logger.py
vulcan/core/utils/number.py
vulcan/core/utils/token_helper.py
vulcan_ms_core-2023.2.17.20.10.dist-info/WHEEL
vulcan_ms_core-2023.2.17.20.10.dist-info/METADATA
vulcan_ms_core-2023.2.17.20.10.dist-info/RECORD
